COPYING.txt
MANIFEST.in
README.txt
gl3.h
setup.py
examples/__init__.py
examples/depthtexture.py
examples/imageviewer.py
examples/introduction.py
examples/mandelbrot.py
examples/meshview.py
examples/minimalframebufferexample.py
examples/opencl.py
examples/openclstructs.py
examples/opencltexture.py
examples/opencltexture2.py
examples/pointcloud.py
examples/qt.py
examples/simple.py
examples/volumerenderer.py
examples/voxelization.py
glitter/__init__.py
glitter.egg-info/PKG-INFO
glitter.egg-info/SOURCES.txt
glitter.egg-info/dependency_links.txt
glitter.egg-info/requires.txt
glitter.egg-info/top_level.txt
glitter/arrays/__init__.py
glitter/arrays/arraybuffer.py
glitter/arrays/basebuffer.py
glitter/arrays/elementarray.py
glitter/arrays/misc.py
glitter/arrays/vertexarray.py
glitter/contexts/__init__.py
glitter/contexts/bufferproxy.py
glitter/contexts/context.py
glitter/contexts/contextmanager.py
glitter/contexts/drawbuffers.py
glitter/contexts/glut.py
glitter/contexts/glx.py
glitter/contexts/multiproxies.py
glitter/contexts/proxies.py
glitter/contexts/qt.py
glitter/contexts/textures.py
glitter/convenience/__init__.py
glitter/convenience/clinterop.py
glitter/convenience/copying.py
glitter/convenience/defaultpipeline.py
glitter/convenience/grid.py
glitter/convenience/matrices.py
glitter/convenience/mesh.py
glitter/convenience/pipeline.py
glitter/framebuffers/__init__.py
glitter/framebuffers/framebuffer.py
glitter/framebuffers/renderbuffer.py
glitter/misc/__init__.py
glitter/misc/memorybarrier.py
glitter/misc/query.py
glitter/misc/sync.py
glitter/misc/transformfeedback.py
glitter/raw/__init__.py
glitter/raw/constant.py
glitter/raw/errcheck.py
glitter/raw/gl.py
glitter/raw/glew.py
glitter/raw/glu.py
glitter/raw/glut.py
glitter/raw/glx.py
glitter/raw/logger.py
glitter/raw/nv.py
glitter/shaders/__init__.py
glitter/shaders/attribute.py
glitter/shaders/programpipeline.py
glitter/shaders/shader.py
glitter/shaders/shaderprogram.py
glitter/shaders/uniform.py
glitter/textures/__init__.py
glitter/textures/sampler.py
glitter/textures/texture.py
glitter/utils/__init__.py
glitter/utils/constants.py
glitter/utils/dtypes.py
