Metadata-Version: 1.1
Name: glitter
Version: 0.1.7
Summary: Intuitive OpenGL wrappers
Home-page: http://packages.python.org/glitter
Author: Stephan Wenger
Author-email: wenger@cg.cs.tu-bs.de
License: MIT
Download-URL: http://pypi.python.org/pypi/glitter
Keywords: opengl,graphics
Platform: UNKNOWN
Classifier: Programming Language :: Python
Classifier: Programming Language :: Python :: 2
Classifier: License :: OSI Approved :: MIT License
Classifier: Operating System :: OS Independent
Classifier: Operating System :: POSIX :: Linux
Classifier: Development Status :: 3 - Alpha
Classifier: Environment :: Other Environment
Classifier: Intended Audience :: Developers
Classifier: Topic :: Multimedia :: Graphics
Classifier: Topic :: Multimedia :: Graphics :: 3D Rendering
Classifier: Topic :: Software Development :: Libraries
